synkronoida/__init__.py
synkronoida/__main__.py
synkronoida/api.py
synkronoida/cli.py
synkronoida-2023.7.7.dist-info/LICENSE
synkronoida-2023.7.7.dist-info/METADATA
synkronoida-2023.7.7.dist-info/WHEEL
synkronoida-2023.7.7.dist-info/entry_points.txt
synkronoida-2023.7.7.dist-info/top_level.txt
synkronoida-2023.7.7.dist-info/RECORD
